dbcache/__init__.py
dbcache/api.py
dbcache/app.py
dbcache/cli.py
dbcache/http.py
dbcache/schema.py
dbcache/schema.sql
dbcache/testutil.py
dbcache/wsgi.py
dbcache-0.5.0.dist-info/LICENSE
dbcache-0.5.0.dist-info/METADATA
dbcache-0.5.0.dist-info/WHEEL
dbcache-0.5.0.dist-info/entry_points.txt
dbcache-0.5.0.dist-info/top_level.txt
dbcache-0.5.0.dist-info/RECORD
