Metadata-Version: 2.2
Name: dbcache
Version: 0.5.0
Summary: A postgresql backed cache system 
Home-page: https://hg.sr.ht/~pythonian/dbcache
Author: Aurelien Campeas
Author-email: aurelien.campeas@pythonian.fr
Classifier: Development Status :: 4 - Beta
Classifier: Intended Audience :: Developers
Classifier: License :: OSI Approved :: GNU Lesser General Public License v3 (LGPLv3)
Classifier: Operating System :: OS Independent
Classifier: Programming Language :: Python :: 3
Classifier: Topic :: Database
Classifier: Topic :: System :: Distributed Computing
Classifier: Topic :: Software Development :: Object Brokering
License-File: LICENSE
Requires-Dist: flask<3
Requires-Dist: flask-restx
Requires-Dist: python-dateutil
Requires-Dist: sqlhelp
Requires-Dist: sqlalchemy<2
Requires-Dist: pytz
Dynamic: author
Dynamic: author-email
Dynamic: classifier
Dynamic: description
Dynamic: description-content-type
Dynamic: home-page
Dynamic: requires-dist
Dynamic: summary
